embedstore/__init__.py
embedstore/helpers/api.py
embedstore/helpers/exceptions.py
embedstore/rag/datadownloaders.py
embedstore/rag/retrievers.py
embedstore/tools/factcheck.py
embedstore-0.0.6.dist-info/LICENSE
embedstore-0.0.6.dist-info/METADATA
embedstore-0.0.6.dist-info/WHEEL
embedstore-0.0.6.dist-info/top_level.txt
embedstore-0.0.6.dist-info/RECORD
