Metadata-Version: 2.1
Name: embedstore
Version: 0.0.6
Summary: Retrieving the most relevant context for your LLMs
License: MIT License
Requires-Python: <4.0,>=3.8.1
License-File: LICENSE
Requires-Dist: requests (>=2)
